qface_qtro-1.4.1.dist-info/DESCRIPTION.rst
qface_qtro-1.4.1.dist-info/METADATA
qface_qtro-1.4.1.dist-info/RECORD
qface_qtro-1.4.1.dist-info/WHEEL
qface_qtro-1.4.1.dist-info/entry_points.txt
qface_qtro-1.4.1.dist-info/metadata.json
qface_qtro-1.4.1.dist-info/top_level.txt
qtro/__about__.py
qtro/__init__.py
qtro/qtro.py
qtro/templates/CMakeLists.txt
qtro/templates/__init__.py
qtro/templates/libproject.pro
qtro/templates/project.pri
qtro/templates/project.pro
qtro/templates/qmake.conf
qtro/templates/apps/apps.pro
qtro/templates/apps/app/app.pro
qtro/templates/apps/app/main.cpp
qtro/templates/apps/app/qml.qrc
qtro/templates/apps/app/qtquickcontrols2.conf
qtro/templates/apps/app/qml/Main.qml
qtro/templates/clients/__init__.py
qtro/templates/clients/clients.pro
qtro/templates/clients/qmake.conf
qtro/templates/clients/client/CMakeLists.txt
qtro/templates/clients/client/__init__.py
qtro/templates/clients/client/client.pro
qtro/templates/clients/client/docs/__init__.py
qtro/templates/clients/client/docs/docs.pri
qtro/templates/clients/client/docs/online.qdocconf
qtro/templates/clients/client/docs/project.qdocconf
qtro/templates/clients/client/lib/__init__.py
qtro/templates/clients/client/lib/interface.cpp
qtro/templates/clients/client/lib/interface.h
qtro/templates/clients/client/lib/lib.pri
qtro/templates/clients/client/lib/lib.pro
qtro/templates/clients/client/lib/uselib.pri
qtro/templates/clients/client/lib/generated/__init__.py
qtro/templates/clients/client/lib/generated/abstractinterface.cpp
qtro/templates/clients/client/lib/generated/abstractinterface.h
qtro/templates/clients/client/lib/generated/core.cpp
qtro/templates/clients/client/lib/generated/core.h
qtro/templates/clients/client/lib/generated/generated.pri
qtro/templates/clients/client/plugin/__init__.py
qtro/templates/clients/client/plugin/plugin.cpp
qtro/templates/clients/client/plugin/plugin.h
qtro/templates/clients/client/plugin/plugin.pro
qtro/templates/clients/client/plugin/qmldir
qtro/templates/servers/__init__.py
qtro/templates/servers/servers.pro
qtro/templates/servers/server/CMakeLists.txt
qtro/templates/servers/server/__init__.py
qtro/templates/servers/server/main.cpp
qtro/templates/servers/server/meta.json
