Metadata-Version: 2.0
Name: qface-qtro
Version: 1.4.1
Summary: Generator based on the QFace library for QtRemoteObjects
Home-page: https://github.com/Pelagicore/qface-qtro
Author: jryannel
Author-email: juergen@ryannel.org
License: MIT
Keywords: qt ipc generator
Platform: UNKNOWN
Classifier: Development Status :: 3 - Alpha
Classifier: Intended Audience :: Developers
Classifier: Topic :: Software Development :: Code Generators
Classifier: License :: OSI Approved :: MIT License
Classifier: Programming Language :: Python :: 3
Requires-Dist: Jinja2
Requires-Dist: PyYAML
Requires-Dist: click
Requires-Dist: path.py
Requires-Dist: qface (>=1.8)
